LICENSE
rtd_redirects.py
rtd_redirects-1.1.0.dist-info/entry_points.txt
rtd_redirects-1.1.0.dist-info/LICENSE
rtd_redirects-1.1.0.dist-info/WHEEL
rtd_redirects-1.1.0.dist-info/METADATA
rtd_redirects-1.1.0.dist-info/RECORD
