Metadata-Version: 2.1
Name: rtd-redirects
Version: 1.1.0
Summary: Manage redirects in the ReadTheDocs admin, programmatically
Home-page: https://github.com/honzajavorek/rtd-redirects
License: MIT
Keywords: readthedocs,documentation,redirects,sphinx,mkdocs
Author: Honza Javorek
Author-email: mail@honzajavorek.cz
Requires-Python: >=3.6,<4.0
Classifier: Development Status :: 5 - Production/Stable
Classifier: Intended Audience :: Developers
Classifier: Intended Audience :: Information Technology
Classifier: License :: OSI Approved :: MIT License
Classifier: Programming Language :: Python
Classifier: Programming Language :: Python :: 3
Classifier: Programming Language :: Python :: 3 :: Only
Classifier: Programming Language :: Python :: 3.6
Classifier: Programming Language :: Python :: 3.7
Classifier: Programming Language :: Python :: 3.8
Classifier: Programming Language :: Python :: 3.9
Classifier: Topic :: Documentation
Classifier: Topic :: Documentation :: Sphinx
Classifier: Topic :: Internet
Classifier: Topic :: Software Development :: Documentation
Requires-Dist: click (>=7.1.2,<8.0.0)
Requires-Dist: cssselect (>=1.1.0,<2.0.0)
Requires-Dist: lxml (>=4.6.1,<5.0.0)
Requires-Dist: pyaml (>=20.4.0,<21.0.0)
Requires-Dist: requests (>=2.25.0,<3.0.0)
Project-URL: Repository, https://github.com/honzajavorek/rtd-redirects
